{
  "accountID": 4885,
  "SKU": "HOLISTER_OTTOMAN",
  "country": "us",
  "containerID": "#put-viewer-here",
  "presentation": "threesixty",
  "ARQuickLook": true,
  "progressBar": true,
  "focusOnFeatureChange": false,
  "alternateContentZoom": true,
  "fullscreen": true,
  "imageTimeout": 0,
  "startFrame": 1,
  "styleshots": true,
  "styleshotsZoom": true,
  "thumbs": true,
  "threeSixty": true,
  "tooltipCarouselText": "Click to Zoom",
  "tooltipStackedText": "Click to Zoom",
  "zoom": true,
  "zoomButton": null,
  "tooltipStackedPosition": "1",
  "format": "jpg",
  "zoomBackgroundColor": "FFFFFF",
  "features": [
    "LEGS",
    "CHOCOLATE",
    "1",
    "MOURACESP"
  ],
  "backgroundColor": "FFFFFF",
  "debug": false,
  "missingCombinationErrorText": "Sorry, we don not have images for the requested feature set",
  "thumbPageSize": 5,
  "tooltipAltImgText": "Click to Zoom",
  "tooltipDragText": "Drag to Rotate, Click to Zoom",
  "tooltipStyleshotText": "Click to Zoom",
  "tooltipZoomText": "Move the Mouse to Pan",
  "thumbCount": 5,
  "title": "360 HD product view",
  "maxZoom": "4k"
}